aptos_sdk/__init__.py
aptos_sdk/account.py
aptos_sdk/account_address.py
aptos_sdk/account_sequence_number.py
aptos_sdk/aptos_cli_wrapper.py
aptos_sdk/aptos_token_client.py
aptos_sdk/aptos_tokenv1_client.py
aptos_sdk/asymmetric_crypto.py
aptos_sdk/asymmetric_crypto_wrapper.py
aptos_sdk/async_client.py
aptos_sdk/authenticator.py
aptos_sdk/bcs.py
aptos_sdk/cli.py
aptos_sdk/ed25519.py
aptos_sdk/metadata.py
aptos_sdk/package_publisher.py
aptos_sdk/secp256k1_ecdsa.py
aptos_sdk/sync_client.py
aptos_sdk/transaction_worker.py
aptos_sdk/transactions.py
aptos_sdk/type_tag.py
aptos_sdk_fork-0.7.1a2.dist-info/METADATA
aptos_sdk_fork-0.7.1a2.dist-info/WHEEL
aptos_sdk_fork-0.7.1a2.dist-info/RECORD
